{
  "generator-jhipster": {
    "applicationType": "monolith",
    "authenticationType": "jwt",
    "baseName": "kebaby",
    "blueprints": [],
    "buildTool": "maven",
    "cacheProvider": "memcached",
    "clientFramework": "react",
    "clientPackageManager": "npm",
    "clientTheme": "none",
    "clientThemeVariant": "",
    "creationTimestamp": 1643118549008,
    "databaseType": "sql",
    "devDatabaseType": "mysql",
    "devServerPort": 9060,
    "dtoSuffix": "DTO",
    "enableGradleEnterprise": false,
    "enableHibernateCache": false,
    "enableSwaggerCodegen": "true",
    "enableTranslation": true,
    "entitySuffix": "",
    "gitCompany": "",
    "jhiPrefix": "jhi",
    "jhipsterVersion": "7.6.0",
    "jwtSecretKey": "OTQ5YzA1MmNmNmQ2NjgyODEyMGY0MWViMDVhNmI0ZjQ3Njk1MmFjNzIyODYwNjMyMTk5MjQ1ZDkwN2VjODkyYWY2ZmE4YTcxMjE1NzUyMjUxYmE2NmVlMWU2NzQxZmQ5YjUzNjJkNGY3YmNjYzBhZTdiYjljZjY0NzUxNDhiZDc=",
    "languages": ["fr", "en"],
    "messageBroker": "kafka",
    "nativeLanguage": "fr",
    "otherModules": [],
    "packageFolder": "com/mycompany/kebaby",
    "packageName": "com.mycompany.kebaby",
    "pages": [],
    "prodDatabaseType": "mysql",
    "reactive": false,
    "searchEngine": "elasticsearch",
    "serverPort": 8080,
    "serviceDiscoveryType": "eureka",
    "skipCheckLengthOfIdentifier": false,
    "skipFakeData": false,
    "skipUserManagement": false,
    "testFrameworks": ["gatling"],
    "useSass": true,
    "websocket": "spring-websocket",
    "withAdminUi": true
  },
  "git-provider": "GitHub",
  "git-company": "sosolution59300",
  "repository-name": "kebaby"
}
